get_profile/__init__.py
get_profile/get_profile.py
get_profile/helpers.py
get_profile-0.0.2.dist-info/LICENSE
get_profile-0.0.2.dist-info/METADATA
get_profile-0.0.2.dist-info/WHEEL
get_profile-0.0.2.dist-info/top_level.txt
get_profile-0.0.2.dist-info/RECORD
