Metadata-Version: 2.1
Name: get-profile
Version: 0.0.2
Summary: Quickly profile your code with a single line of code.
Author: Sonny George
Author-email: <sonnygeorge5@gmail.com>
License: UNKNOWN
Keywords: python,profiling,profile,runtime,decorator,cprofile
Platform: UNKNOWN
Classifier: Intended Audience :: Developers
Classifier: Programming Language :: Python :: 3
Classifier: Operating System :: Unix
Classifier: Operating System :: MacOS :: MacOS X
Classifier: Operating System :: Microsoft :: Windows
License-File: LICENSE
Requires-Dist: pandas
Requires-Dist: numpy
